mdi/__init__.py
mdi-1.0.dist-info/LICENSE
mdi-1.0.dist-info/METADATA
mdi-1.0.dist-info/WHEEL
mdi-1.0.dist-info/entry_points.txt
mdi-1.0.dist-info/top_level.txt
mdi-1.0.dist-info/RECORD
